dotjs.py
dotjs-1.0.4.dist-info/LICENSE
dotjs-1.0.4.dist-info/METADATA
dotjs-1.0.4.dist-info/WHEEL
dotjs-1.0.4.dist-info/entry_points.txt
dotjs-1.0.4.dist-info/top_level.txt
dotjs-1.0.4.dist-info/RECORD
