Metadata-Version: 2.1
Name: dotjs
Version: 1.0.4
Summary: A Python implementation of the dotjs HTTP server
Home-page: https://github.com/hackedd/python-dotjs
Author: Paul Hooijenga
Author-email: paulhooijenga@gmail.com
License: MIT
Platform: UNKNOWN
Classifier: Development Status :: 4 - Beta
Classifier: Environment :: Console
Classifier: Intended Audience :: Developers
Classifier: License :: OSI Approved :: MIT License
Classifier: Operating System :: OS Independent
Classifier: Programming Language :: Python
Classifier: Programming Language :: Python :: 2
Classifier: Programming Language :: Python :: 3
